{
    "height": 984,
    "width": 1000,
    "rectangles": [
        {
            "x": 451,
            "y": 537,
            "width": 412,
            "height": 388,
            "color": [
                255,
                255,
                255
            ],
            "color_id": "white"
        },
        {
            "x": 863,
            "y": 537,
            "width": 137,
            "height": 264,
            "color": [
                181,
                102,
                0
            ],
            "color_id": "blue"
        },
        {
            "x": 0,
            "y": 537,
            "width": 451,
            "height": 447,
            "color": [
                255,
                255,
                255
            ],
            "color_id": "white"
        },
        {
            "x": 863,
            "y": 801,
            "width": 137,
            "height": 183,
            "color": [
                255,
                255,
                255
            ],
            "color_id": "white"
        },
        {
            "x": 451,
            "y": 925,
            "width": 412,
            "height": 59,
            "color": [
                255,
                255,
                255
            ],
            "color_id": "white"
        },
        {
            "x": 451,
            "y": 0,
            "width": 549,
            "height": 537,
            "color": [
                255,
                255,
                255
            ],
            "color_id": "white"
        },
        {
            "x": 0,
            "y": 0,
            "width": 451,
            "height": 537,
            "color": [
                31,
                21,
                238
            ],
            "color_id": "red"
        }
    ],
    "options": {
        "binary_threshold": 110,
        "min_line_length": 70,
        "min_distance_factor": 0.073,
        "black_rectangle_dilate": 33
    }
}