{
  "id": "A114",
  "database": "https://rkd.nl/en/explore/images/262365",
  "link": "http://catalogue.pietmondrian.nl/amsterdam-2-circa-1897-1901-a92-a259/figures-a112-a145/#262365",
  "thumbnail": "http://imagehandler.rkd.nl/wwwopac.ashx?command=getcontent&server=images&value=jpg\\686\\1001245686.jpg&width=150&height=150",
  "year": "1828",
  "description": " Piet\u00a0Mondriaan\n      \u00a0  \n\n    Portrait of Egbert Kuipers (1828-1892) and Jantje Wiegersma (1828-...) c. 1900-1901oil paint / canvas, 84\n        x\n        54\u00a0cmAmsterdam\n          (Christie's), 1987-05-21,\n          no. 480A114",
  "state": 0
}