{
  "id": "A173",
  "database": "https://rkd.nl/en/explore/images/263327",
  "link": "http://catalogue.pietmondrian.nl/amsterdam-2-circa-1897-1901-a92-a259/landscapes-het-gooi-a165-a176/#263327",
  "thumbnail": "http://imagehandler.rkd.nl/wwwopac.ashx?command=getcontent&server=images&value=jpg\\947\\1001204947.jpg&width=150&height=150",
  "description": " Piet\u00a0Mondriaan\n      \u00a0  \n\n    Farmstead in Het Gooi, viewed between trees and over fence 1898-1899oil paint / cardboard, 45,5\n        x\n        56\u00a0cmGemeentemuseum Den Haag, The Hague, no.\u00a0100-1971 / 0334258A173"
}