{
  "id": "A30",
  "database": "https://rkd.nl/en/explore/images/261209",
  "link": "http://catalogue.pietmondrian.nl/amsterdam-i-circa-1893-1897-a23-a49/#261209",
  "thumbnail": "http://imagehandler.rkd.nl/wwwopac.ashx?command=getcontent&server=images&value=jpg\\856\\1001199856.jpg&width=150&height=150",
  "year": "1893",
  "description": " Piet\u00a0Mondriaan\n      \u00a0  \n\n    The Singel with round Lutheran church 1893-1895oil paint / canvas, 69\n        x\n        46\u00a0cmGemeentemuseum Den Haag, The Hague, no.\u00a098-1971 / 0334256A30"
}