{
  "id": "A671",
  "database": "https://rkd.nl/en/explore/images/269727",
  "link": "http://catalogue.pietmondrian.nl/amsterdam-5-circa-1908-1911-a594-a673/landscapes-a648-a673/#269727",
  "thumbnail": "http://imagehandler.rkd.nl/wwwopac.ashx?command=getcontent&server=images&value=jpg\\631\\1001212631.jpg&width=150&height=150",
  "description": " Piet\u00a0Mondriaan\n      \u00a0  \n\n    Evening 1908-1910oil paint / canvas, 70\n        x\n        99\u00a0cmGemeentemuseum Den Haag, The Hague, no.\u00a017-1933 / 0332041A671"
}