{
  "id": "B105",
  "database": "https://rkd.nl/en/explore/images/272625",
  "link": "http://catalogue.pietmondrian.nl/paris-2-1920-1937-b104-b281.312/1920-1921-b104-b132/#272625",
  "thumbnail": "http://imagehandler.rkd.nl/wwwopac.ashx?command=getcontent&server=images&value=jpg\\229\\1001240229.jpg&width=150&height=150",
  "description": " Piet\u00a0Mondriaan\n      \u00a0  \n\n    Composition A 1920oil paint / canvas, 90\n        x\n        91\u00a0cmGalleria Nazionale d'Arte Moderna \n           (Rome), Rome, no.\u00a05519B105"
}