{
  "id": "B144",
  "database": "https://rkd.nl/en/explore/images/251380",
  "link": "http://catalogue.pietmondrian.nl/paris-2-1920-1937-b104-b281.312/1922-1923-b133-b150/#251380",
  "thumbnail": "http://imagehandler.rkd.nl/wwwopac.ashx?command=getcontent&server=images&value=jpg\\570\\1001244570.jpg&width=150&height=150",
  "year": "1922",
  "description": " Piet\u00a0Mondriaan\n      \u00a0  \n\n    Composition with large red plane, bluish gray, yellow, black, and blue dated 1922oil paint / canvas, 54\n        x\n        53,4\u00a0cmPrivate collectionB144"
}