{
  "id": "B188",
  "database": "https://rkd.nl/en/explore/images/253083",
  "link": "http://catalogue.pietmondrian.nl/paris-2-1920-1937-b104-b281.312/1927-1928-b182-b205/#253083",
  "thumbnail": "http://imagehandler.rkd.nl/wwwopac.ashx?command=getcontent&server=images&value=jpg\\765\\1001240765.jpg&width=150&height=150",
  "description": " Piet\u00a0Mondriaan\n      \u00a0  \n\n    Composition with red, yellow, and blue dated 1927oil paint / canvas, 51,1\n        x\n        51,1\u00a0cm The\u00a0Cleveland Museum of Art, Cleveland (Ohio), no.\u00a01967.215B188"
}