{
  "id": "B195",
  "database": "https://rkd.nl/en/explore/images/253212",
  "link": "http://catalogue.pietmondrian.nl/paris-2-1920-1937-b104-b281.312/1927-1928-b182-b205/#253212",
  "thumbnail": "http://imagehandler.rkd.nl/wwwopac.ashx?command=getcontent&server=images&value=jpg\\764\\1001240764.jpg&width=150&height=150",
  "year": "1927",
  "description": " Piet\u00a0Mondriaan\n      \u00a0  \n\n    Composition with red, blue, and gray dated 1927oil paint / canvas, 66\n        x\n        50\u00a0cmLondon (England)\n          (Sotheby's), 2014-06-23\n           - 2014-06-24,\n          no. 14B195",
  "state": 0
}