{
  "id": "B325",
  "database": "https://rkd.nl/en/explore/images/275184",
  "link": "http://catalogue.pietmondrian.nl/drawings-1925-1943-b325-b370/#275184",
  "thumbnail": "http://imagehandler.rkd.nl/wwwopac.ashx?command=getcontent&server=images&value=jpg\\756\\1001240756.jpg&width=150&height=150",
  "description": " Piet\u00a0Mondriaan\n      \u00a0  \n\n    Sheet A: three square compositions / verso: two lozenge compositions 1925charcoal / paper, 230\n        x\n        298\u00a0mmPrivate collectionB325"
}