{
  "id": "B70",
  "database": "https://rkd.nl/en/explore/images/271434",
  "link": "http://catalogue.pietmondrian.nl/nederland-1914-1919-b57-b103/#271434",
  "thumbnail": "http://imagehandler.rkd.nl/wwwopac.ashx?command=getcontent&server=images&value=jpg\\313\\1001241313.jpg&width=150&height=150",
  "description": " Piet\u00a0Mondriaan\n      \u00a0  \n\n    Pier and ocean 4 dated 1914charcoal / paper, 502\n        x\n        628\u00a0mmGemeentemuseum Den Haag, The Hague, no.\u00a0T 128-1971 / 0557358B70"
}