{
  "id": "C15",
  "database": "https://rkd.nl/en/explore/images/275842",
  "link": "http://catalogue.pietmondrian.nl/catalogue-of-late-naturalistic-works-c1-c155/landscapes-c1-c20/#275842",
  "thumbnail": "http://imagehandler.rkd.nl/wwwopac.ashx?command=getcontent&server=images&value=jpg\\823\\1001233823.jpg&width=150&height=150",
  "description": " Piet\u00a0Mondriaan\n      \u00a0  \n\n    Windmill in the evening c. 1917charcoal / paper, 1030\n        x\n        835\u00a0mmGemeentemuseum Den Haag, The Hague, no.\u00a0T 130-1971 / 0320973C15"
}